MANIFEST.in
README.txt
setup.cfg
setup.py
anthill/__init__.py
anthill.tal.macrorenderer.egg-info/PKG-INFO
anthill.tal.macrorenderer.egg-info/SOURCES.txt
anthill.tal.macrorenderer.egg-info/dependency_links.txt
anthill.tal.macrorenderer.egg-info/entry_points.txt
anthill.tal.macrorenderer.egg-info/namespace_packages.txt
anthill.tal.macrorenderer.egg-info/not-zip-safe
anthill.tal.macrorenderer.egg-info/requires.txt
anthill.tal.macrorenderer.egg-info/top_level.txt
anthill/tal/__init__.py
anthill/tal/macrorenderer/.engine.py.swp
anthill/tal/macrorenderer/__init__.py
anthill/tal/macrorenderer/engine.py
docs/HISTORY.txt