Metadata-Version: 1.0
Name: anthill.tal.macrorenderer
Version: 0.2.1
Summary: Rendering ZPT macros from python code made easy
Home-page: UNKNOWN
Author: Simon Pamies
Author-email: s.pamies@banality.de
License: GPL
Keywords: zope zpt macros render python
Platform: UNKNOWN
Classifier: Programming Language :: Python
Classifier: Topic :: Software Development :: Libraries :: Python Modules
